{"paths": {"dir_github": "/n/data1/hms/neurobio/sabatini/josh/github_repos", "fileName_save_model": "EfficientNet_b0_7unfrozen_simCLR", "path_data_training": "/n/data1/hms/neurobio/sabatini/josh/github_repos/GCaMP_ROI_classifier/data/sparse/sf_sparse_36x36_20220503.npz"}, "prefs": {"saveModelIteratively": true, "saveLogs": true}, "useGPU_training": true, "useGPU_dataloader": false, "dataloader_kwargs": {"batch_size": 1024, "shuffle": true, "drop_last": true, "pin_memory": true, "num_workers": 36, "persistent_workers": true, "prefetch_factor": 4}, "torchvision_model": "convnext_tiny", "pre_head_fc_sizes": [128, 128], "post_head_fc_sizes": [128], "block_to_unfreeze": "1.2", "n_block_toInclude": 4, "lr": 0.0001, "weight_decay": 0.0, "gamma": 1.0, "n_epochs": 9999999, "temperature": 0.5, "l2_alpha": 0.0, "augmentation": {"Scale_image_sum": {"sum_val": 1, "epsilon": 1e-09, "min_sub": true}, "AddPoissonNoise": {"scaler_bounds": [10000, 100000], "prob": 0.5, "base": 1000, "scaling": "log"}, "Horizontal_stripe_scale": {"alpha_min_max": [0.5, 1], "im_size": [36, 36], "prob": 0.5}, "Horizontal_stripe_shift": {"alpha_min_max": [1, 3], "im_size": [36, 36], "prob": 0.5}, "RandomHorizontalFlip": {"p": 0.5}, "RandomAffine": {"degrees": [-180, 180], "translate": [0.1, 0.1], "scale": [0.6, 1.2], "shear": [-15, 15, -15, 15], "interpolation": "bilinear", "fill": 0, "fillcolor": null, "resample": null}, "AddGaussianNoise": {"mean": 0, "std": 0.001, "prob": 0.5}, "ScaleDynamicRange": {"scaler_bounds": [0, 1], "epsilon": 1e-09}, "WarpPoints": {"r": [0.3, 0.6], "cx": [-0.3, 0.3], "cy": [-0.3, 0.3], "dx": [-0.24, 0.24], "dy": [-0.24, 0.24], "n_warps": 2, "prob": 0.5, "img_size_in": [36, 36], "img_size_out": [72, 72]}, "TileChannels": {"dim": 0, "n_channels": 3}}}